nilva_session/__init__.py
nilva_session/admin/__init__.py
nilva_session/admin/user_session.py
nilva_session/apis/__init__.py
nilva_session/apis/view.py
nilva_session/apps.py
nilva_session/backends/__init__.py
nilva_session/backends/db/__init__.py
nilva_session/backends/db/jwt_authentication.py
nilva_session/backends/db/mixin_authentication.py
nilva_session/backends/db/token_authentication.py
nilva_session/migrations/0001_initial.py
nilva_session/migrations/__init__.py
nilva_session/models/__init__.py
nilva_session/models/user_session.py
nilva_session/serializers/__init__.py
nilva_session/serializers/session_serializer.py
nilva_session/serializers/token_serializer.py
nilva_session/settings.py
nilva_session/urls.py
nilva_session/utils.py
nilva_session-0.1.5.dist-info/LICENSE
nilva_session-0.1.5.dist-info/METADATA
nilva_session-0.1.5.dist-info/WHEEL
nilva_session-0.1.5.dist-info/RECORD
