Metadata-Version: 2.3
Name: nilva-session
Version: 0.1.5
Summary: This module provides a robust and secure implementation of user session management based on **database-backed token authentication**, with features like caching, session expiration, user agent validation, and session invalidation.
Author: ali minuei
Requires-Python: >=3.11
Classifier: Programming Language :: Python :: 3
Classifier: Programming Language :: Python :: 3.11
Classifier: Programming Language :: Python :: 3.12
Classifier: Programming Language :: Python :: 3.13
Requires-Dist: django (>=5.1,<6.0)
Requires-Dist: djangorestframework (>=3.15,<4.0)
Requires-Dist: djangorestframework-simplejwt (>=5.4.0)
Requires-Dist: user-agents (>=2.2)
